[
  {
    "title": "The Rock \"Final Boss\" #168 Funko Pop - WWE - Special Edition",
    "image": "https://www.popfigures.com/cdn/shop/files/The_Rock_168_Funko_pop.jpg?v=1742327655&width=1512",
    "link": "https://www.popfigures.com/products/the-rock-final-boss-168-funko-pop-wwe-special-edition?_pos=2&_sid=bbec429e3&_ss=r",
    "price": "Sale price\n£12.49"
  },
  {
    "title": "Iyo Sky #171 Funko Pop - WWE ",
    "image": "https://www.popfigures.com/cdn/shop/files/Iyo_Sky_funko_pop.jpg?v=1738749326&width=1512",
    "link": "https://www.popfigures.com/products/iyo-sky-171-funko-pop-wwe?_pos=3&_sid=bbec429e3&_ss=r",
    "price": "Sale price\n£12.49"
  },
  {
    "title": "La Knight #172 Funko Pop - WWE ",
    "image": "https://www.popfigures.com/cdn/shop/files/eef4fc29-0f38-4cd4-be68-66d2008d1bf2.jpg?v=1738683691&width=1512",
    "link": "https://www.popfigures.com/products/la-knight-172-funko-pop-wwe?_pos=4&_sid=bbec429e3&_ss=r",
    "price": "Sale price\n£12.49"
  },
  {
    "title": "Hulk Hogan #149 Funko Pop! - WWE",
    "image": "https://www.popfigures.com/cdn/shop/files/Hulk_Hogan_149_Funko_Pop_-_WWE.jpg?v=1727693198&width=1512",
    "link": "https://www.popfigures.com/products/hulk-hogan-149-funko-pop-wwe?_pos=5&_sid=bbec429e3&_ss=r",
    "price": "Sale price\n£11.49"
  },
  {
    "title": "John Cena #177 Funko Pop! - WWE - Fanatics Exclusive",
    "image": "https://www.popfigures.com/cdn/shop/files/John_Cena_177_Funko_Pop_-_WWE_-_Fanatics_Exclusive_Box.jpg?v=1741089962&width=1512",
    "link": "https://www.popfigures.com/products/john-cena-177-funko-pop-wwe-fanatics-exclusive?_pos=6&_sid=bbec429e3&_ss=r",
    "price": "Sale price\n£24.99"
  },
  {
    "title": "The Miz #169 Funko Pop! - WWE",
    "image": "https://www.popfigures.com/cdn/shop/files/The_Miz_169_Funko_Pop_-_WWE_-_PREORDER.jpg?v=1727693680&width=1512",
    "link": "https://www.popfigures.com/products/the-miz-169-funko-pop-wwe?_pos=7&_sid=bbec429e3&_ss=r",
    "price": "Sale price\n£11.99"
  },
  {
    "title": "Montez Ford #95 Funko Pop! WWE",
    "image": "https://www.popfigures.com/cdn/shop/products/Montez_Ford_95_Funko_Pop_-_WWE.jpg?v=1727697201&width=1200",
    "link": "https://www.popfigures.com/products/wwe-street-profits?_pos=8&_sid=bbec429e3&_ss=r",
    "price": "Sale price\n£11.49"
  },
  {
    "title": "Razor Ramon #161 Funko Pop! - WWE",
    "image": "https://www.popfigures.com/cdn/shop/files/Razor_Ramon_161_Funko_Pop_-_WWE.jpg?v=1727700933&width=1170",
    "link": "https://www.popfigures.com/products/razor-ramon-161-funko-pop-wwe?_pos=9&_sid=bbec429e3&_ss=r",
    "price": "Sale price\n£11.49"
  },
  {
    "title": "Dusty Rhodes #114 Funko Pop! WWE",
    "image": "https://www.popfigures.com/cdn/shop/products/Dusty_Rhodes_114_Funko_Pop_WWE.png?v=1727692908&width=1512",
    "link": "https://www.popfigures.com/products/dusty-rhodes-114-funko-pop-wwe?_pos=10&_sid=bbec429e3&_ss=r",
    "price": "Sale price\n£11.49"
  },
  {
    "title": "Vader #138 Funko Pop! - WWE",
    "image": "https://www.popfigures.com/cdn/shop/files/Vader_WWE_138_Funko.jpg?v=1727696925&width=1512",
    "link": "https://www.popfigures.com/products/vader-138-funko-pop-wwe?_pos=11&_sid=bbec429e3&_ss=r",
    "price": "Sale price\n£11.49"
  },
  {
    "title": "The Rock #91 Funko Pop! WWE - Entertainment Earth Exclusive",
    "image": "https://www.popfigures.com/cdn/shop/products/The_Rock_91_Funko_Pop_WWE_-_Entertainment_Earth_Exclusivec2.jpg?v=1727772363&width=1800",
    "link": "https://www.popfigures.com/products/wwe-the-rock-w-championship-belt-entertainment-earth-exclusive-preorder?_pos=12&_sid=bbec429e3&_ss=r",
    "price": "Sale price\n£25.03"
  },
  {
    "title": "British Bulldog #126 Funko Pop! WWE",
    "image": "https://www.popfigures.com/cdn/shop/files/British_Bulldog_126_Funko_Pop_WWE.jpg?v=1727773603&width=1512",
    "link": "https://www.popfigures.com/products/british-bulldog-126-funko-pop-wwe-preorder?_pos=13&_sid=bbec429e3&_ss=r",
    "price": "Sale price\n£11.49"
  },
  {
    "title": "The Rock #137 Funko Pop! - WWE",
    "image": "https://www.popfigures.com/cdn/shop/files/The_Rock_137_Funko_Pop_-_WWE.jpg?v=1727693564&width=1512",
    "link": "https://www.popfigures.com/products/the-rock-137-funko-pop-wwe?_pos=14&_sid=bbec429e3&_ss=r",
    "price": "Sale price\n£11.49"
  },
  {
    "title": "King Booker #128 Funko Pop! WWE",
    "image": "https://www.popfigures.com/cdn/shop/files/King_Booker_WWE.jpg?v=1727691817&width=1512",
    "link": "https://www.popfigures.com/products/king-booker-128-funko-pop-wwe?_pos=15&_sid=bbec429e3&_ss=r",
    "price": "Sale price\n£11.49"
  },
  {
    "title": "Triple H (Skull King) #139 Funko Pop! Deluxe - WWE",
    "image": "https://www.popfigures.com/cdn/shop/files/Triple_H_Skull_King_139_Funko_Pop_Deluxe_-_WWE.jpg?v=1727694349&width=1512",
    "link": "https://www.popfigures.com/products/triple-h-skull-king-139-funko-pop-deluxe-wwe?_pos=16&_sid=bbec429e3&_ss=r",
    "price": "Sale price\n£27.50"
  },
  {
    "title": "Braun Strowman #145 Funko Pop! - WWE",
    "image": "https://www.popfigures.com/cdn/shop/files/WWE_Brian_Strowman_Funko.jpg?v=1727691548&width=1512",
    "link": "https://www.popfigures.com/products/braun-strowman-145-funko-pop-wwe?_pos=17&_sid=bbec429e3&_ss=r",
    "price": "Sale price\n£11.49"
  },
  {
    "title": "\"Rowdy\" Roddy Piper #147 Funko Pop! - WWE",
    "image": "https://www.popfigures.com/cdn/shop/files/Rowdy_Roddy_Piper_147_Funko_Pop_-_WWE.jpg?v=1727692005&width=1512",
    "link": "https://www.popfigures.com/products/rowdy-roddy-piper-147-funko-pop-wwe?_pos=19&_sid=bbec429e3&_ss=r",
    "price": "Sale price\n£11.49"
  },
  {
    "title": "Kurt Angle #146 Funko Pop! - WWE",
    "image": "https://www.popfigures.com/cdn/shop/files/Kurt_Angle_WWE.jpg?v=1727691380&width=1512",
    "link": "https://www.popfigures.com/products/kurt-angle-146-funko-pop-wwe?_pos=20&_sid=bbec429e3&_ss=r",
    "price": "Sale price\n£11.49"
  },
  {
    "title": "Eddie Guerrero #155 Funko Pop! WWE",
    "image": "https://www.popfigures.com/cdn/shop/files/Eddie_Guerrero_155_Funko_Pop_WWE.jpg?v=1727769684&width=1512",
    "link": "https://www.popfigures.com/products/eddie-guerrero-155-funko-pop-wwe?_pos=21&_sid=bbec429e3&_ss=r",
    "price": "Sale price\n£11.49"
  },
  {
    "title": "Shawn Michaels #141 Funko Pop - WWE ",
    "image": "https://www.popfigures.com/cdn/shop/files/4d161494-1c76-4416-9819-59d943e2d932.jpg?v=1738750395&width=1512",
    "link": "https://www.popfigures.com/products/shawn-michaels-173-funko-pop-wwe?_pos=22&_sid=bbec429e3&_ss=r",
    "price": "Sale price\n£12.49"
  },
  {
    "title": "X-Pac #174 Funko Pop - WWE ",
    "image": "https://www.popfigures.com/cdn/shop/files/a8cb32e2-aee7-425d-8604-fea305e771ef.jpg?v=1738751193&width=1512",
    "link": "https://www.popfigures.com/products/x-pac-174-funko-pop-wwe?_pos=23&_sid=bbec429e3&_ss=r",
    "price": "Sale price\n£12.49"
  },
  {
    "title": "Beth Phoenix #127 Funko Pop! - WWE",
    "image": "https://www.popfigures.com/cdn/shop/files/image_26d165ec-8020-4ac3-8e6c-fa1717cbf76b.jpg?v=1688112551&width=1512",
    "link": "https://www.popfigures.com/products/beth-phoenix-127-funko-pop-wwe?_pos=24&_sid=bbec429e3&_ss=r",
    "price": "Sale price\n£11.49"
  },
  {
    "title": "“Macho Man” Randy Savage #79 Funko Pop! WWE",
    "image": "https://www.popfigures.com/cdn/shop/products/wwe-macho-man-randy-savage-857838.jpg?v=1608295998&width=737",
    "link": "https://www.popfigures.com/products/wwe-macho-man-randy-savage?_pos=25&_sid=bbec429e3&_ss=r",
    "price": "Sale price\n£27.30"
  },
  {
    "title": "Zelina Vega #160 Funko Pop! - WWE",
    "image": "https://www.popfigures.com/cdn/shop/files/Zelina_Vega_160_Funko_Pop_-_WWE.jpg?v=1727772584&width=1170",
    "link": "https://www.popfigures.com/products/zelina-vega-160-funko-pop-wwe?_pos=26&_sid=bbec429e3&_ss=r",
    "price": "Sale price\n£11.49"
  },
  {
    "title": "Rikishi #150 Funko Pop! - WWE - Target Exclusive",
    "image": "https://www.popfigures.com/cdn/shop/files/Rikishi_150_Funko_Pop_-_WWE_-_Target_Exclusive.jpg?v=1727773136&width=2048",
    "link": "https://www.popfigures.com/products/rikishi-150-funko-pop-wwe-target-exclusive?_pos=27&_sid=bbec429e3&_ss=r",
    "price": "Sale price\n£24.99"
  },
  {
    "title": "Rocky Maivia #120 Funko Pop! - WWE",
    "image": "https://www.popfigures.com/cdn/shop/files/Rocky_Maivia_120_Funko_Pop_-_WWE_-_Box.jpg?v=1730304127&width=1512",
    "link": "https://www.popfigures.com/products/rocky-maivia-120-funko-pop-wwe?_pos=28&_sid=bbec429e3&_ss=r",
    "price": "Sale price\n£9.99"
  },
  {
    "title": "Triple H and Ronda Rousey 2 Pack Funko Pop! - WWE",
    "image": "https://www.popfigures.com/cdn/shop/files/Triple_H_and_Ronda_Rousey_2_Pack_Funko_Pop_-_WWE.jpg?v=1727696515&width=1512",
    "link": "https://www.popfigures.com/products/triple-h-and-ronda-rousey-2-pack-funko-pop-wwe?_pos=29&_sid=bbec429e3&_ss=r",
    "price": "Sale price\n£19.99"
  },
  {
    "title": "Shotzi #148 Funko Pop! - WWE",
    "image": "https://www.popfigures.com/cdn/shop/files/Shotzi_WWE_Funko.jpg?v=1727691711&width=1512",
    "link": "https://www.popfigures.com/products/shotzi-148-funko-pop-wwe?_pos=30&_sid=bbec429e3&_ss=r",
    "price": "Sale price\n£11.49"
  },
  {
    "title": "Angelo Dawkins #94 Funko Pop! WWE",
    "image": "https://www.popfigures.com/cdn/shop/products/Angelo_Dawkins_94_Funko.jpg?v=1727695779&width=1200",
    "link": "https://www.popfigures.com/products/wwe-street-profits-angelo-dawkins-preorder?_pos=31&_sid=bbec429e3&_ss=r",
    "price": "Sale price\n£11.49"
  },
  {
    "title": "Brock Lesnar #110 Funko Pop! WWE - Amazon Exclusive",
    "image": "https://www.popfigures.com/cdn/shop/products/Brock_Lesnar_110_Funko_Pop_WWE_-_Amazon_Exclusive.jpg?v=1727698136&width=499",
    "link": "https://www.popfigures.com/products/brock-lesnar-110-funko-pop-wwe-amazon-exclusive?_pos=32&_sid=bbec429e3&_ss=r",
    "price": "Sale price\n£25.00"
  },
  {
    "title": "Riddle #115 Funko Pop! WWE",
    "image": "https://www.popfigures.com/cdn/shop/products/Riddle_115_Funko_Pop_WWE.png?v=1727695434&width=1512",
    "link": "https://www.popfigures.com/products/riddle-115-funko-pop-wwe-preorder?_pos=33&_sid=bbec429e3&_ss=r",
    "price": "Sale price\n£11.49"
  },
  {
    "title": "Hollywood Hulk Hogan #165 Funko Pop! - WWE - Fanatics Exclusive",
    "image": "https://www.popfigures.com/cdn/shop/files/Hollywood_Hulk_Hogan_165_Fanatics_Funko.jpg?v=1727700690&width=1512",
    "link": "https://www.popfigures.com/products/hollywood-hulk-hogan-165-funko-pop-wwe-fanatics-exclusive?_pos=34&_sid=bbec429e3&_ss=r",
    "price": "Sale price\n£24.99"
  },
  {
    "title": "Hulk Hogan #71 Funko Pop! - WWE - Special Edition",
    "image": "https://www.popfigures.com/cdn/shop/files/Hulk_Hogan_71_Funko_Pop_-_WWE_-_Special_Edition.jpg?v=1727700182&width=1512",
    "link": "https://www.popfigures.com/products/hulk-hogan-71-funko-pop-wwe-special-edition?_pos=35&_sid=bbec429e3&_ss=r",
    "price": "Sale price\n£14.99"
  },
  {
    "title": "Mr. America #162 Funko Pop! - WWE",
    "image": "https://www.popfigures.com/cdn/shop/files/Mr._America_162_Funko_Pop_-_WWE.jpg?v=1727698920&width=1170",
    "link": "https://www.popfigures.com/products/mr-america-162-funko-pop-wwe?_pos=36&_sid=bbec429e3&_ss=r",
    "price": "Sale price\n£11.49"
  },
  {
    "title": "Jerry Lawler (Metallic) #97 Funko Pop! WWE",
    "image": "https://www.popfigures.com/cdn/shop/products/Jerry_Lawler_97_Metallic_Funko_Pop_-_WWE.jpg?v=1727697628&width=1200",
    "link": "https://www.popfigures.com/products/wwe-jerry-lawler?_pos=37&_sid=bbec429e3&_ss=r",
    "price": "Sale price\n£14.49"
  },
  {
    "title": "Razor Ramon 4 Pack Bitty Funko POP! - WWE - Chance Of Chase",
    "image": "https://www.popfigures.com/cdn/shop/files/Razor_Ramon_4_Pack_Bitty_Funko_POP_-_WWE_-_Chance_Of_Chase.jpg?v=1727692381&width=1512",
    "link": "https://www.popfigures.com/products/razor-ramon-4-pack-bitty-funko-pop-wwe-chance-of-chase?_pos=38&_sid=bbec429e3&_ss=r",
    "price": "Sale price\n£9.99"
  },
  {
    "title": "(NWO) Hogan & The Outsiders Funko Pop! 3 Pack WWE",
    "image": "https://www.popfigures.com/cdn/shop/files/NWO_Hogan_amp_The_Outsiders_Funko_Pop_3_Pack_WWE.jpg?v=1727774287&width=1512",
    "link": "https://www.popfigures.com/products/nwo-hogan-the-outsiders-funko-pop-3-pack-wwe?_pos=39&_sid=bbec429e3&_ss=r",
    "price": "Sale price\n£29.99"
  },
  {
    "title": "Lex Luger #159 Funko Pop! - WWE",
    "image": "https://www.popfigures.com/cdn/shop/files/Lex_Luger_159_Funko_Pop_-_WWE.jpg?v=1727701175&width=1170",
    "link": "https://www.popfigures.com/products/lex-luger-159-funko-pop-wwe?_pos=40&_sid=bbec429e3&_ss=r",
    "price": "Sale price\n£11.49"
  },
  {
    "title": "Dude Love #109 Funko Pop! - WWE",
    "image": "https://www.popfigures.com/cdn/shop/files/Dude_Love_109_Funko_Pop_-_WWE_Box.jpg?v=1743667885&width=1512",
    "link": "https://www.popfigures.com/products/dude-love-109-funko-pop-wwe?_pos=41&_sid=bbec429e3&_ss=r",
    "price": "Sale price\n£10.99"
  },
  {
    "title": "Gunther #170 Funko Pop - WWE",
    "image": "https://www.popfigures.com/cdn/shop/files/654b5dda-d0d3-4a9d-8107-e2761c69ff69.jpg?v=1738750750&width=1512",
    "link": "https://www.popfigures.com/products/gunther-170-funko-pop-wwe?_pos=42&_sid=bbec429e3&_ss=r",
    "price": "Sale price\n£12.49"
  },
  {
    "title": "Umaga #157 Funko Pop! - WWE - Fanatics Exclusive",
    "image": "https://www.popfigures.com/cdn/shop/files/Umaga_157_Funko_Pop_-_WWE_-_Fanatics_Exclusive.jpg?v=1727770324&width=1512",
    "link": "https://www.popfigures.com/products/umaga-157-funko-pop-wwe-fanatics-exclusive?_pos=43&_sid=bbec429e3&_ss=r",
    "price": "Sale price\n£24.99"
  },
  {
    "title": "“Macho Man” Randy Savage #83 Funko Pop! - WWE - Walmart Exclusive",
    "image": "https://www.popfigures.com/cdn/shop/files/Macho_Man_Randy_Savage_83_Funko_Pop_-_WWE_-_Walmart_Exclusive.jpg?v=1727773870&width=1512",
    "link": "https://www.popfigures.com/products/macho-man-randy-savage-walmart-exclusive-pop-vinyl?_pos=44&_sid=bbec429e3&_ss=r",
    "price": "Sale price\n£19.99"
  },
  {
    "title": "Hulk Hogan & Mr. T Deluxe 2 Pack Vinyl! WWE, Amazon Exclusive",
    "image": "https://www.popfigures.com/cdn/shop/products/hulk-hogan-mr-t-amazon-exclusive-2-pack-691616.jpg?v=1621958364&width=750",
    "link": "https://www.popfigures.com/products/hulk-hogan-mr-t-amazon-exclusive-2-pack?_pos=45&_sid=bbec429e3&_ss=r",
    "price": "Sale price\n£24.99"
  },
  {
    "title": "‘Ravishing’ Rick Rude #140 Funko Pop! - WWE",
    "image": "https://www.popfigures.com/cdn/shop/files/Ravishing_Rick_Rude_140_Funko_Pop_WWE.jpg?v=1727694571&width=1512",
    "link": "https://www.popfigures.com/products/ravishing-rick-rude-140-funko-pop-wwe?_pos=46&_sid=bbec429e3&_ss=r",
    "price": "Sale price\n£11.49"
  },
  {
    "title": "Diamond Dallas Page #166 Funko Pop! - WWE",
    "image": "https://www.popfigures.com/cdn/shop/files/Diamond_Dallas_Page_166_Funko_Pop_-_WWE.jpg?v=1727693932&width=1512",
    "link": "https://www.popfigures.com/products/diamond-dallas-page-166-funko-pop-wwe?_pos=47&_sid=bbec429e3&_ss=r",
    "price": "Sale price\n£11.99"
  },
  {
    "title": "Bret \"Hit Man\" Hart 4 Pack Bitty Funko POP! - WWE - Chance Of Chase",
    "image": "https://www.popfigures.com/cdn/shop/files/Bret_Hit_Man_Hart_4_Pack_Bitty_Funko_POP_-_WWE_-_Chance_Of_Chase.jpg?v=1727691942&width=1512",
    "link": "https://www.popfigures.com/products/bret-hit-man-hart-4-pack-bitty-funko-pop-wwe-chance-of-chase?_pos=48&_sid=bbec429e3&_ss=r",
    "price": "Sale price\n£9.99"
  }
]